stkclient/__init__.py
stkclient/__main__.py
stkclient/api.py
stkclient/model.py
stkclient/py.typed
stkclient/signer.py
stkclient-0.1.1.dist-info/entry_points.txt
stkclient-0.1.1.dist-info/LICENSE.rst
stkclient-0.1.1.dist-info/WHEEL
stkclient-0.1.1.dist-info/METADATA
stkclient-0.1.1.dist-info/RECORD
