Metadata-Version: 2.1
Name: stkclient
Version: 0.1.1
Summary: Send To Kindle
Home-page: https://github.com/maxdjohnson/stkclient
License: MIT
Author: Max Johnson
Author-email: maxdjohnson@gmail.com
Requires-Python: >=3.7,<4.0
Classifier: Development Status :: 4 - Beta
Classifier: License :: OSI Approved :: MIT License
Classifier: Programming Language :: Python :: 3
Classifier: Programming Language :: Python :: 3.10
Classifier: Programming Language :: Python :: 3.7
Classifier: Programming Language :: Python :: 3.8
Classifier: Programming Language :: Python :: 3.9
Requires-Dist: defusedxml (>=0.7.1,<0.8.0)
Requires-Dist: rsa (>=4.8,<5.0)
Project-URL: Changelog, https://github.com/maxdjohnson/stkclient/releases
Project-URL: Documentation, https://stkclient.readthedocs.io
Project-URL: Repository, https://github.com/maxdjohnson/stkclient
